miPaquete/__init__.py
miPaquete/modulo1.py
miPaquete/modulo2.py
miPaqueteSuperRandom-0.7.dist-info/METADATA
miPaqueteSuperRandom-0.7.dist-info/WHEEL
miPaqueteSuperRandom-0.7.dist-info/top_level.txt
miPaqueteSuperRandom-0.7.dist-info/RECORD
